charge_power/__init__.py
charge_power/__main__.py
charge_power/charge/__init__.py
charge_power/charge/print_charge.py
charge_power-0.1.1.dist-info/LICENSE
charge_power-0.1.1.dist-info/METADATA
charge_power-0.1.1.dist-info/WHEEL
charge_power-0.1.1.dist-info/entry_points.txt
charge_power-0.1.1.dist-info/RECORD
