Metadata-Version: 2.1
Name: charge-power
Version: 0.1.1
Summary: Small utility to track current charge/discharge wattage based on system sensors (Linux only)
Home-page: https://github.com/kanootoko/charge-power
License: MIT
Author: Aleksei Sokol
Author-email: kanootoko@gmail.com
Requires-Python: >=3.9,<4.0
Classifier: License :: OSI Approved :: MIT License
Classifier: Operating System :: POSIX :: Linux
Classifier: Programming Language :: Python :: 3
Classifier: Programming Language :: Python :: 3.9
Classifier: Programming Language :: Python :: 3.10
Classifier: Programming Language :: Python :: 3.11
Classifier: Topic :: System :: Hardware
Requires-Dist: click (>=8.1.4,<9.0.0)
Requires-Dist: rich (>=13.4.2,<14.0.0)
Project-URL: Bug tracker, https://github.com/kanootoko/charge-power/issues
Project-URL: Repository, https://github.com/kanootoko/charge-power
